LICENSE.txt
MANIFEST.in
README.rst
requirements.txt
setup.py
docs/Makefile
docs/__init__.py
docs/basic.rst
docs/conf.py
docs/context.rst
docs/exceptions.rst
docs/ext.rst
docs/faq.rst
docs/index.rst
docs/install.rst
docs/messages.rst
docs/tutorial.rst
wechat_python_sdk.egg-info/PKG-INFO
wechat_python_sdk.egg-info/SOURCES.txt
wechat_python_sdk.egg-info/dependency_links.txt
wechat_python_sdk.egg-info/pbr.json
wechat_python_sdk.egg-info/requires.txt
wechat_python_sdk.egg-info/top_level.txt
wechat_sdk/__init__.py
wechat_sdk/basic.py
wechat_sdk/exceptions.py
wechat_sdk/ext.py
wechat_sdk/lib.py
wechat_sdk/messages.py
wechat_sdk/reply.py
wechat_sdk/context/__init__.py
wechat_sdk/context/framework/__init__.py
wechat_sdk/context/framework/django/__init__.py
wechat_sdk/context/framework/django/apps.py
wechat_sdk/context/framework/django/exceptions.py
wechat_sdk/context/framework/django/models.py
wechat_sdk/context/framework/django/serializers.py
wechat_sdk/context/framework/django/tests.py
wechat_sdk/context/framework/django/backends/__init__.py
wechat_sdk/context/framework/django/backends/base.py
wechat_sdk/context/framework/django/backends/db.py
wechat_sdk/context/framework/django/migrations/0001_initial.py
wechat_sdk/context/framework/django/migrations/__init__.py