Metadata-Version: 1.0
Name: wechat-python-sdk
Version: 0.6.1
Summary: 微信公众平台Python开发包
Home-page: https://github.com/bowenpay/wechat-python-sdk
Author: doraemonext jingpingyi
Author-email: doraemonext@gmail.com, jingping.yi@gmail.com
License: BSD License
Keywords: wechat,sdk,wechat sdk
Platform: any
